{
  "@context": {
    "@language": "en",
    "@vocab": "https://schema.org/",
    "column": "ml:column",
    "data": {
      "@id": "ml:data",
      "@type": "@json"
    },
    "dataType": {
      "@id": "ml:dataType",
      "@type": "@vocab"
    },
    "extract": "ml:extract",
    "field": "ml:field",
    "fileProperty": "ml:fileProperty",
    "format": "ml:format",
    "includes": "ml:includes",
    "isEnumeration": "ml:isEnumeration",
    "jsonPath": "ml:jsonPath",
    "ml": "http://mlcommons.org/schema/",
    "parentField": "ml:parentField",
    "path": "ml:path",
    "recordSet": "ml:recordSet",
    "references": "ml:references",
    "regex": "ml:regex",
    "repeated": "ml:repeated",
    "replace": "ml:replace",
    "sc": "https://schema.org/",
    "separator": "ml:separator",
    "source": "ml:source",
    "subField": "ml:subField",
    "transform": "ml:transform"
  },
  "@type": "sc:Dataset",
  "name": "birds",
  "description": "Multi-label dataset. The birds dataset consists of 327 audio\n  recordings of 12 different vocalizing bird species. Each sound can be\n  assigned to various bird species.",
  "citation": "https://core.ac.uk/download/pdf/10195210.pdf",
  "license": "Public",
  "url": "https://www.openml.org/search?type=data&id=41464",
  "distribution": [
    {
      "@type": "sc:FileObject",
      "name": "birds.arff",
      "contentUrl": "https://api.openml.org/data/v1/download/21230421/birds.arff",
      "encodingFormat": "text/plain",
      "md5": "6c69596d2dbd1add5e9a22352fa71e30"
    }
  ],
  "recordSet": [
    {
      "@type": "ml:RecordSet",
      "name": "birds_records",
      "field": [
        {
          "@type": "ml:Field",
          "name": "audio_ssd1",
          "dataType": "sc:Integer",
          "source": {
            "distribution": "birds.arff",
            "extract": {
              "column": "audio.ssd1"
            }
          }
        },
        {
          "@type": "ml:Field",
          "name": "audio_ssd2",
          "dataType": "sc:Integer",
          "source": {
            "distribution": "birds.arff",
            "extract": {
              "column": "audio.ssd2"
            }
          }
        },
        {
          "@type": "ml:Field",
          "name": "audio_ssd3",
          "dataType": "sc:Integer",
          "source": {
            "distribution": "birds.arff",
            "extract": {
              "column": "audio.ssd3"
            }
          }
        },
        {
          "@type": "ml:Field",
          "name": "audio_ssd4",
          "dataType": "sc:Integer",
          "source": {
            "distribution": "birds.arff",
            "extract": {
              "column": "audio.ssd4"
            }
          }
        },
        {
          "@type": "ml:Field",
          "name": "audio_ssd5",
          "dataType": "sc:Integer",
          "source": {
            "distribution": "birds.arff",
            "extract": {
              "column": "audio.ssd5"
            }
          }
        },
        {
          "@type": "ml:Field",
          "name": "audio_ssd6",
          "dataType": "sc:Integer",
          "source": {
            "distribution": "birds.arff",
            "extract": {
              "column": "audio.ssd6"
            }
          }
        },
        {
          "@type": "ml:Field",
          "name": "audio_ssd7",
          "dataType": "sc:Integer",
          "source": {
            "distribution": "birds.arff",
            "extract": {
              "column": "audio.ssd7"
            }
          }
        },
        {
          "@type": "ml:Field",
          "name": "audio_ssd8",
          "dataType": "sc:Integer",
          "source": {
            "distribution": "birds.arff",
            "extract": {
              "column": "audio.ssd8"
            }
          }
        },
        {
          "@type": "ml:Field",
          "name": "audio_ssd9",
          "dataType": "sc:Integer",
          "source": {
            "distribution": "birds.arff",
            "extract": {
              "column": "audio.ssd9"
            }
          }
        },
        {
          "@type": "ml:Field",
          "name": "audio_ssd10",
          "dataType": "sc:Integer",
          "source": {
            "distribution": "birds.arff",
            "extract": {
              "column": "audio.ssd10"
            }
          }
        },
        {
          "@type": "ml:Field",
          "name": "audio_ssd11",
          "dataType": "sc:Integer",
          "source": {
            "distribution": "birds.arff",
            "extract": {
              "column": "audio.ssd11"
            }
          }
        },
        {
          "@type": "ml:Field",
          "name": "audio_ssd12",
          "dataType": "sc:Integer",
          "source": {
            "distribution": "birds.arff",
            "extract": {
              "column": "audio.ssd12"
            }
          }
        },
        {
          "@type": "ml:Field",
          "name": "audio_ssd13",
          "dataType": "sc:Integer",
          "source": {
            "distribution": "birds.arff",
            "extract": {
              "column": "audio.ssd13"
            }
          }
        },
        {
          "@type": "ml:Field",
          "name": "audio_ssd14",
          "dataType": "sc:Integer",
          "source": {
            "distribution": "birds.arff",
            "extract": {
              "column": "audio.ssd14"
            }
          }
        },
        {
          "@type": "ml:Field",
          "name": "audio_ssd15",
          "dataType": "sc:Integer",
          "source": {
            "distribution": "birds.arff",
            "extract": {
              "column": "audio.ssd15"
            }
          }
        },
        {
          "@type": "ml:Field",
          "name": "audio_ssd16",
          "dataType": "sc:Integer",
          "source": {
            "distribution": "birds.arff",
            "extract": {
              "column": "audio.ssd16"
            }
          }
        },
        {
          "@type": "ml:Field",
          "name": "audio_ssd17",
          "dataType": "sc:Integer",
          "source": {
            "distribution": "birds.arff",
            "extract": {
              "column": "audio.ssd17"
            }
          }
        },
        {
          "@type": "ml:Field",
          "name": "audio_ssd18",
          "dataType": "sc:Integer",
          "source": {
            "distribution": "birds.arff",
            "extract": {
              "column": "audio.ssd18"
            }
          }
        },
        {
          "@type": "ml:Field",
          "name": "audio_ssd19",
          "dataType": "sc:Integer",
          "source": {
            "distribution": "birds.arff",
            "extract": {
              "column": "audio.ssd19"
            }
          }
        },
        {
          "@type": "ml:Field",
          "name": "audio_ssd20",
          "dataType": "sc:Integer",
          "source": {
            "distribution": "birds.arff",
            "extract": {
              "column": "audio.ssd20"
            }
          }
        },
        {
          "@type": "ml:Field",
          "name": "audio_ssd21",
          "dataType": "sc:Integer",
          "source": {
            "distribution": "birds.arff",
            "extract": {
              "column": "audio.ssd21"
            }
          }
        },
        {
          "@type": "ml:Field",
          "name": "audio_ssd22",
          "dataType": "sc:Integer",
          "source": {
            "distribution": "birds.arff",
            "extract": {
              "column": "audio.ssd22"
            }
          }
        },
        {
          "@type": "ml:Field",
          "name": "audio_ssd25",
          "dataType": "sc:Integer",
          "source": {
            "distribution": "birds.arff",
            "extract": {
              "column": "audio.ssd25"
            }
          }
        },
        {
          "@type": "ml:Field",
          "name": "audio_ssd26",
          "dataType": "sc:Integer",
          "source": {
            "distribution": "birds.arff",
            "extract": {
              "column": "audio.ssd26"
            }
          }
        },
        {
          "@type": "ml:Field",
          "name": "audio_ssd27",
          "dataType": "sc:Integer",
          "source": {
            "distribution": "birds.arff",
            "extract": {
              "column": "audio.ssd27"
            }
          }
        },
        {
          "@type": "ml:Field",
          "name": "audio_ssd28",
          "dataType": "sc:Integer",
          "source": {
            "distribution": "birds.arff",
            "extract": {
              "column": "audio.ssd28"
            }
          }
        },
        {
          "@type": "ml:Field",
          "name": "audio_ssd29",
          "dataType": "sc:Integer",
          "source": {
            "distribution": "birds.arff",
            "extract": {
              "column": "audio.ssd29"
            }
          }
        },
        {
          "@type": "ml:Field",
          "name": "audio_ssd30",
          "dataType": "sc:Integer",
          "source": {
            "distribution": "birds.arff",
            "extract": {
              "column": "audio.ssd30"
            }
          }
        },
        {
          "@type": "ml:Field",
          "name": "audio_ssd31",
          "dataType": "sc:Integer",
          "source": {
            "distribution": "birds.arff",
            "extract": {
              "column": "audio.ssd31"
            }
          }
        },
        {
          "@type": "ml:Field",
          "name": "audio_ssd32",
          "dataType": "sc:Integer",
          "source": {
            "distribution": "birds.arff",
            "extract": {
              "column": "audio.ssd32"
            }
          }
        },
        {
          "@type": "ml:Field",
          "name": "audio_ssd33",
          "dataType": "sc:Integer",
          "source": {
            "distribution": "birds.arff",
            "extract": {
              "column": "audio.ssd33"
            }
          }
        },
        {
          "@type": "ml:Field",
          "name": "audio_ssd34",
          "dataType": "sc:Integer",
          "source": {
            "distribution": "birds.arff",
            "extract": {
              "column": "audio.ssd34"
            }
          }
        },
        {
          "@type": "ml:Field",
          "name": "audio_ssd35",
          "dataType": "sc:Integer",
          "source": {
            "distribution": "birds.arff",
            "extract": {
              "column": "audio.ssd35"
            }
          }
        },
        {
          "@type": "ml:Field",
          "name": "audio_ssd36",
          "dataType": "sc:Integer",
          "source": {
            "distribution": "birds.arff",
            "extract": {
              "column": "audio.ssd36"
            }
          }
        },
        {
          "@type": "ml:Field",
          "name": "audio_ssd37",
          "dataType": "sc:Integer",
          "source": {
            "distribution": "birds.arff",
            "extract": {
              "column": "audio.ssd37"
            }
          }
        },
        {
          "@type": "ml:Field",
          "name": "audio_ssd38",
          "dataType": "sc:Integer",
          "source": {
            "distribution": "birds.arff",
            "extract": {
              "column": "audio.ssd38"
            }
          }
        },
        {
          "@type": "ml:Field",
          "name": "audio_ssd39",
          "dataType": "sc:Integer",
          "source": {
            "distribution": "birds.arff",
            "extract": {
              "column": "audio.ssd39"
            }
          }
        },
        {
          "@type": "ml:Field",
          "name": "audio_ssd40",
          "dataType": "sc:Integer",
          "source": {
            "distribution": "birds.arff",
            "extract": {
              "column": "audio.ssd40"
            }
          }
        },
        {
          "@type": "ml:Field",
          "name": "audio_ssd41",
          "dataType": "sc:Integer",
          "source": {
            "distribution": "birds.arff",
            "extract": {
              "column": "audio.ssd41"
            }
          }
        },
        {
          "@type": "ml:Field",
          "name": "audio_ssd42",
          "dataType": "sc:Integer",
          "source": {
            "distribution": "birds.arff",
            "extract": {
              "column": "audio.ssd42"
            }
          }
        },
        {
          "@type": "ml:Field",
          "name": "audio_ssd43",
          "dataType": "sc:Integer",
          "source": {
            "distribution": "birds.arff",
            "extract": {
              "column": "audio.ssd43"
            }
          }
        },
        {
          "@type": "ml:Field",
          "name": "audio_ssd44",
          "dataType": "sc:Integer",
          "source": {
            "distribution": "birds.arff",
            "extract": {
              "column": "audio.ssd44"
            }
          }
        },
        {
          "@type": "ml:Field",
          "name": "audio_ssd45",
          "dataType": "sc:Integer",
          "source": {
            "distribution": "birds.arff",
            "extract": {
              "column": "audio.ssd45"
            }
          }
        },
        {
          "@type": "ml:Field",
          "name": "audio_ssd46",
          "dataType": "sc:Integer",
          "source": {
            "distribution": "birds.arff",
            "extract": {
              "column": "audio.ssd46"
            }
          }
        },
        {
          "@type": "ml:Field",
          "name": "audio_ssd49",
          "dataType": "sc:Integer",
          "source": {
            "distribution": "birds.arff",
            "extract": {
              "column": "audio.ssd49"
            }
          }
        },
        {
          "@type": "ml:Field",
          "name": "audio_ssd50",
          "dataType": "sc:Integer",
          "source": {
            "distribution": "birds.arff",
            "extract": {
              "column": "audio.ssd50"
            }
          }
        },
        {
          "@type": "ml:Field",
          "name": "audio_ssd51",
          "dataType": "sc:Integer",
          "source": {
            "distribution": "birds.arff",
            "extract": {
              "column": "audio.ssd51"
            }
          }
        },
        {
          "@type": "ml:Field",
          "name": "audio_ssd52",
          "dataType": "sc:Integer",
          "source": {
            "distribution": "birds.arff",
            "extract": {
              "column": "audio.ssd52"
            }
          }
        },
        {
          "@type": "ml:Field",
          "name": "audio_ssd53",
          "dataType": "sc:Integer",
          "source": {
            "distribution": "birds.arff",
            "extract": {
              "column": "audio.ssd53"
            }
          }
        },
        {
          "@type": "ml:Field",
          "name": "audio_ssd54",
          "dataType": "sc:Integer",
          "source": {
            "distribution": "birds.arff",
            "extract": {
              "column": "audio.ssd54"
            }
          }
        },
        {
          "@type": "ml:Field",
          "name": "audio_ssd55",
          "dataType": "sc:Integer",
          "source": {
            "distribution": "birds.arff",
            "extract": {
              "column": "audio.ssd55"
            }
          }
        },
        {
          "@type": "ml:Field",
          "name": "audio_ssd56",
          "dataType": "sc:Integer",
          "source": {
            "distribution": "birds.arff",
            "extract": {
              "column": "audio.ssd56"
            }
          }
        },
        {
          "@type": "ml:Field",
          "name": "audio_ssd57",
          "dataType": "sc:Integer",
          "source": {
            "distribution": "birds.arff",
            "extract": {
              "column": "audio.ssd57"
            }
          }
        },
        {
          "@type": "ml:Field",
          "name": "audio_ssd58",
          "dataType": "sc:Integer",
          "source": {
            "distribution": "birds.arff",
            "extract": {
              "column": "audio.ssd58"
            }
          }
        },
        {
          "@type": "ml:Field",
          "name": "audio_ssd59",
          "dataType": "sc:Integer",
          "source": {
            "distribution": "birds.arff",
            "extract": {
              "column": "audio.ssd59"
            }
          }
        },
        {
          "@type": "ml:Field",
          "name": "audio_ssd60",
          "dataType": "sc:Integer",
          "source": {
            "distribution": "birds.arff",
            "extract": {
              "column": "audio.ssd60"
            }
          }
        },
        {
          "@type": "ml:Field",
          "name": "audio_ssd61",
          "dataType": "sc:Integer",
          "source": {
            "distribution": "birds.arff",
            "extract": {
              "column": "audio.ssd61"
            }
          }
        },
        {
          "@type": "ml:Field",
          "name": "audio_ssd62",
          "dataType": "sc:Integer",
          "source": {
            "distribution": "birds.arff",
            "extract": {
              "column": "audio.ssd62"
            }
          }
        },
        {
          "@type": "ml:Field",
          "name": "audio_ssd63",
          "dataType": "sc:Integer",
          "source": {
            "distribution": "birds.arff",
            "extract": {
              "column": "audio.ssd63"
            }
          }
        },
        {
          "@type": "ml:Field",
          "name": "audio_ssd64",
          "dataType": "sc:Integer",
          "source": {
            "distribution": "birds.arff",
            "extract": {
              "column": "audio.ssd64"
            }
          }
        },
        {
          "@type": "ml:Field",
          "name": "audio_ssd65",
          "dataType": "sc:Integer",
          "source": {
            "distribution": "birds.arff",
            "extract": {
              "column": "audio.ssd65"
            }
          }
        },
        {
          "@type": "ml:Field",
          "name": "audio_ssd66",
          "dataType": "sc:Integer",
          "source": {
            "distribution": "birds.arff",
            "extract": {
              "column": "audio.ssd66"
            }
          }
        },
        {
          "@type": "ml:Field",
          "name": "audio_ssd67",
          "dataType": "sc:Integer",
          "source": {
            "distribution": "birds.arff",
            "extract": {
              "column": "audio.ssd67"
            }
          }
        },
        {
          "@type": "ml:Field",
          "name": "audio_ssd68",
          "dataType": "sc:Integer",
          "source": {
            "distribution": "birds.arff",
            "extract": {
              "column": "audio.ssd68"
            }
          }
        },
        {
          "@type": "ml:Field",
          "name": "audio_ssd69",
          "dataType": "sc:Integer",
          "source": {
            "distribution": "birds.arff",
            "extract": {
              "column": "audio.ssd69"
            }
          }
        },
        {
          "@type": "ml:Field",
          "name": "audio_ssd70",
          "dataType": "sc:Integer",
          "source": {
            "distribution": "birds.arff",
            "extract": {
              "column": "audio.ssd70"
            }
          }
        },
        {
          "@type": "ml:Field",
          "name": "audio_ssd73",
          "dataType": "sc:Integer",
          "source": {
            "distribution": "birds.arff",
            "extract": {
              "column": "audio.ssd73"
            }
          }
        },
        {
          "@type": "ml:Field",
          "name": "audio_ssd74",
          "dataType": "sc:Integer",
          "source": {
            "distribution": "birds.arff",
            "extract": {
              "column": "audio.ssd74"
            }
          }
        },
        {
          "@type": "ml:Field",
          "name": "audio_ssd75",
          "dataType": "sc:Integer",
          "source": {
            "distribution": "birds.arff",
            "extract": {
              "column": "audio.ssd75"
            }
          }
        },
        {
          "@type": "ml:Field",
          "name": "audio_ssd76",
          "dataType": "sc:Integer",
          "source": {
            "distribution": "birds.arff",
            "extract": {
              "column": "audio.ssd76"
            }
          }
        },
        {
          "@type": "ml:Field",
          "name": "audio_ssd77",
          "dataType": "sc:Integer",
          "source": {
            "distribution": "birds.arff",
            "extract": {
              "column": "audio.ssd77"
            }
          }
        },
        {
          "@type": "ml:Field",
          "name": "audio_ssd78",
          "dataType": "sc:Integer",
          "source": {
            "distribution": "birds.arff",
            "extract": {
              "column": "audio.ssd78"
            }
          }
        },
        {
          "@type": "ml:Field",
          "name": "audio_ssd79",
          "dataType": "sc:Integer",
          "source": {
            "distribution": "birds.arff",
            "extract": {
              "column": "audio.ssd79"
            }
          }
        },
        {
          "@type": "ml:Field",
          "name": "audio_ssd80",
          "dataType": "sc:Integer",
          "source": {
            "distribution": "birds.arff",
            "extract": {
              "column": "audio.ssd80"
            }
          }
        },
        {
          "@type": "ml:Field",
          "name": "audio_ssd81",
          "dataType": "sc:Integer",
          "source": {
            "distribution": "birds.arff",
            "extract": {
              "column": "audio.ssd81"
            }
          }
        },
        {
          "@type": "ml:Field",
          "name": "audio_ssd82",
          "dataType": "sc:Integer",
          "source": {
            "distribution": "birds.arff",
            "extract": {
              "column": "audio.ssd82"
            }
          }
        },
        {
          "@type": "ml:Field",
          "name": "audio_ssd83",
          "dataType": "sc:Integer",
          "source": {
            "distribution": "birds.arff",
            "extract": {
              "column": "audio.ssd83"
            }
          }
        },
        {
          "@type": "ml:Field",
          "name": "audio_ssd84",
          "dataType": "sc:Integer",
          "source": {
            "distribution": "birds.arff",
            "extract": {
              "column": "audio.ssd84"
            }
          }
        },
        {
          "@type": "ml:Field",
          "name": "audio_ssd85",
          "dataType": "sc:Integer",
          "source": {
            "distribution": "birds.arff",
            "extract": {
              "column": "audio.ssd85"
            }
          }
        },
        {
          "@type": "ml:Field",
          "name": "audio_ssd86",
          "dataType": "sc:Integer",
          "source": {
            "distribution": "birds.arff",
            "extract": {
              "column": "audio.ssd86"
            }
          }
        },
        {
          "@type": "ml:Field",
          "name": "audio_ssd87",
          "dataType": "sc:Integer",
          "source": {
            "distribution": "birds.arff",
            "extract": {
              "column": "audio.ssd87"
            }
          }
        },
        {
          "@type": "ml:Field",
          "name": "audio_ssd88",
          "dataType": "sc:Integer",
          "source": {
            "distribution": "birds.arff",
            "extract": {
              "column": "audio.ssd88"
            }
          }
        },
        {
          "@type": "ml:Field",
          "name": "audio_ssd89",
          "dataType": "sc:Integer",
          "source": {
            "distribution": "birds.arff",
            "extract": {
              "column": "audio.ssd89"
            }
          }
        },
        {
          "@type": "ml:Field",
          "name": "audio_ssd90",
          "dataType": "sc:Integer",
          "source": {
            "distribution": "birds.arff",
            "extract": {
              "column": "audio.ssd90"
            }
          }
        },
        {
          "@type": "ml:Field",
          "name": "audio_ssd91",
          "dataType": "sc:Integer",
          "source": {
            "distribution": "birds.arff",
            "extract": {
              "column": "audio.ssd91"
            }
          }
        },
        {
          "@type": "ml:Field",
          "name": "audio_ssd92",
          "dataType": "sc:Integer",
          "source": {
            "distribution": "birds.arff",
            "extract": {
              "column": "audio.ssd92"
            }
          }
        },
        {
          "@type": "ml:Field",
          "name": "audio_ssd93",
          "dataType": "sc:Integer",
          "source": {
            "distribution": "birds.arff",
            "extract": {
              "column": "audio.ssd93"
            }
          }
        },
        {
          "@type": "ml:Field",
          "name": "audio_ssd94",
          "dataType": "sc:Integer",
          "source": {
            "distribution": "birds.arff",
            "extract": {
              "column": "audio.ssd94"
            }
          }
        },
        {
          "@type": "ml:Field",
          "name": "audio_ssd97",
          "dataType": "sc:Integer",
          "source": {
            "distribution": "birds.arff",
            "extract": {
              "column": "audio.ssd97"
            }
          }
        },
        {
          "@type": "ml:Field",
          "name": "audio_ssd98",
          "dataType": "sc:Integer",
          "source": {
            "distribution": "birds.arff",
            "extract": {
              "column": "audio.ssd98"
            }
          }
        },
        {
          "@type": "ml:Field",
          "name": "audio_ssd99",
          "dataType": "sc:Integer",
          "source": {
            "distribution": "birds.arff",
            "extract": {
              "column": "audio.ssd99"
            }
          }
        },
        {
          "@type": "ml:Field",
          "name": "audio_ssd100",
          "dataType": "sc:Integer",
          "source": {
            "distribution": "birds.arff",
            "extract": {
              "column": "audio.ssd100"
            }
          }
        },
        {
          "@type": "ml:Field",
          "name": "audio_ssd101",
          "dataType": "sc:Integer",
          "source": {
            "distribution": "birds.arff",
            "extract": {
              "column": "audio.ssd101"
            }
          }
        },
        {
          "@type": "ml:Field",
          "name": "audio_ssd102",
          "dataType": "sc:Integer",
          "source": {
            "distribution": "birds.arff",
            "extract": {
              "column": "audio.ssd102"
            }
          }
        },
        {
          "@type": "ml:Field",
          "name": "audio_ssd103",
          "dataType": "sc:Integer",
          "source": {
            "distribution": "birds.arff",
            "extract": {
              "column": "audio.ssd103"
            }
          }
        },
        {
          "@type": "ml:Field",
          "name": "audio_ssd104",
          "dataType": "sc:Integer",
          "source": {
            "distribution": "birds.arff",
            "extract": {
              "column": "audio.ssd104"
            }
          }
        },
        {
          "@type": "ml:Field",
          "name": "audio_ssd105",
          "dataType": "sc:Integer",
          "source": {
            "distribution": "birds.arff",
            "extract": {
              "column": "audio.ssd105"
            }
          }
        },
        {
          "@type": "ml:Field",
          "name": "audio_ssd106",
          "dataType": "sc:Integer",
          "source": {
            "distribution": "birds.arff",
            "extract": {
              "column": "audio.ssd106"
            }
          }
        },
        {
          "@type": "ml:Field",
          "name": "audio_ssd107",
          "dataType": "sc:Integer",
          "source": {
            "distribution": "birds.arff",
            "extract": {
              "column": "audio.ssd107"
            }
          }
        },
        {
          "@type": "ml:Field",
          "name": "audio_ssd108",
          "dataType": "sc:Integer",
          "source": {
            "distribution": "birds.arff",
            "extract": {
              "column": "audio.ssd108"
            }
          }
        },
        {
          "@type": "ml:Field",
          "name": "audio_ssd109",
          "dataType": "sc:Integer",
          "source": {
            "distribution": "birds.arff",
            "extract": {
              "column": "audio.ssd109"
            }
          }
        },
        {
          "@type": "ml:Field",
          "name": "audio_ssd110",
          "dataType": "sc:Integer",
          "source": {
            "distribution": "birds.arff",
            "extract": {
              "column": "audio.ssd110"
            }
          }
        },
        {
          "@type": "ml:Field",
          "name": "audio_ssd111",
          "dataType": "sc:Integer",
          "source": {
            "distribution": "birds.arff",
            "extract": {
              "column": "audio.ssd111"
            }
          }
        },
        {
          "@type": "ml:Field",
          "name": "audio_ssd112",
          "dataType": "sc:Integer",
          "source": {
            "distribution": "birds.arff",
            "extract": {
              "column": "audio.ssd112"
            }
          }
        },
        {
          "@type": "ml:Field",
          "name": "audio_ssd113",
          "dataType": "sc:Integer",
          "source": {
            "distribution": "birds.arff",
            "extract": {
              "column": "audio.ssd113"
            }
          }
        },
        {
          "@type": "ml:Field",
          "name": "audio_ssd114",
          "dataType": "sc:Integer",
          "source": {
            "distribution": "birds.arff",
            "extract": {
              "column": "audio.ssd114"
            }
          }
        },
        {
          "@type": "ml:Field",
          "name": "audio_ssd115",
          "dataType": "sc:Integer",
          "source": {
            "distribution": "birds.arff",
            "extract": {
              "column": "audio.ssd115"
            }
          }
        },
        {
          "@type": "ml:Field",
          "name": "audio_ssd116",
          "dataType": "sc:Integer",
          "source": {
            "distribution": "birds.arff",
            "extract": {
              "column": "audio.ssd116"
            }
          }
        },
        {
          "@type": "ml:Field",
          "name": "audio_ssd117",
          "dataType": "sc:Integer",
          "source": {
            "distribution": "birds.arff",
            "extract": {
              "column": "audio.ssd117"
            }
          }
        },
        {
          "@type": "ml:Field",
          "name": "audio_ssd118",
          "dataType": "sc:Integer",
          "source": {
            "distribution": "birds.arff",
            "extract": {
              "column": "audio.ssd118"
            }
          }
        },
        {
          "@type": "ml:Field",
          "name": "audio_ssd121",
          "dataType": "sc:Integer",
          "source": {
            "distribution": "birds.arff",
            "extract": {
              "column": "audio.ssd121"
            }
          }
        },
        {
          "@type": "ml:Field",
          "name": "audio_ssd122",
          "dataType": "sc:Integer",
          "source": {
            "distribution": "birds.arff",
            "extract": {
              "column": "audio.ssd122"
            }
          }
        },
        {
          "@type": "ml:Field",
          "name": "audio_ssd123",
          "dataType": "sc:Integer",
          "source": {
            "distribution": "birds.arff",
            "extract": {
              "column": "audio.ssd123"
            }
          }
        },
        {
          "@type": "ml:Field",
          "name": "audio_ssd124",
          "dataType": "sc:Integer",
          "source": {
            "distribution": "birds.arff",
            "extract": {
              "column": "audio.ssd124"
            }
          }
        },
        {
          "@type": "ml:Field",
          "name": "audio_ssd125",
          "dataType": "sc:Integer",
          "source": {
            "distribution": "birds.arff",
            "extract": {
              "column": "audio.ssd125"
            }
          }
        },
        {
          "@type": "ml:Field",
          "name": "audio_ssd126",
          "dataType": "sc:Integer",
          "source": {
            "distribution": "birds.arff",
            "extract": {
              "column": "audio.ssd126"
            }
          }
        },
        {
          "@type": "ml:Field",
          "name": "audio_ssd127",
          "dataType": "sc:Integer",
          "source": {
            "distribution": "birds.arff",
            "extract": {
              "column": "audio.ssd127"
            }
          }
        },
        {
          "@type": "ml:Field",
          "name": "audio_ssd128",
          "dataType": "sc:Integer",
          "source": {
            "distribution": "birds.arff",
            "extract": {
              "column": "audio.ssd128"
            }
          }
        },
        {
          "@type": "ml:Field",
          "name": "audio_ssd129",
          "dataType": "sc:Integer",
          "source": {
            "distribution": "birds.arff",
            "extract": {
              "column": "audio.ssd129"
            }
          }
        },
        {
          "@type": "ml:Field",
          "name": "audio_ssd130",
          "dataType": "sc:Integer",
          "source": {
            "distribution": "birds.arff",
            "extract": {
              "column": "audio.ssd130"
            }
          }
        },
        {
          "@type": "ml:Field",
          "name": "audio_ssd131",
          "dataType": "sc:Integer",
          "source": {
            "distribution": "birds.arff",
            "extract": {
              "column": "audio.ssd131"
            }
          }
        },
        {
          "@type": "ml:Field",
          "name": "audio_ssd132",
          "dataType": "sc:Integer",
          "source": {
            "distribution": "birds.arff",
            "extract": {
              "column": "audio.ssd132"
            }
          }
        },
        {
          "@type": "ml:Field",
          "name": "audio_ssd133",
          "dataType": "sc:Integer",
          "source": {
            "distribution": "birds.arff",
            "extract": {
              "column": "audio.ssd133"
            }
          }
        },
        {
          "@type": "ml:Field",
          "name": "audio_ssd134",
          "dataType": "sc:Integer",
          "source": {
            "distribution": "birds.arff",
            "extract": {
              "column": "audio.ssd134"
            }
          }
        },
        {
          "@type": "ml:Field",
          "name": "audio_ssd135",
          "dataType": "sc:Integer",
          "source": {
            "distribution": "birds.arff",
            "extract": {
              "column": "audio.ssd135"
            }
          }
        },
        {
          "@type": "ml:Field",
          "name": "audio_ssd136",
          "dataType": "sc:Integer",
          "source": {
            "distribution": "birds.arff",
            "extract": {
              "column": "audio.ssd136"
            }
          }
        },
        {
          "@type": "ml:Field",
          "name": "audio_ssd137",
          "dataType": "sc:Integer",
          "source": {
            "distribution": "birds.arff",
            "extract": {
              "column": "audio.ssd137"
            }
          }
        },
        {
          "@type": "ml:Field",
          "name": "audio_ssd138",
          "dataType": "sc:Integer",
          "source": {
            "distribution": "birds.arff",
            "extract": {
              "column": "audio.ssd138"
            }
          }
        },
        {
          "@type": "ml:Field",
          "name": "audio_ssd139",
          "dataType": "sc:Integer",
          "source": {
            "distribution": "birds.arff",
            "extract": {
              "column": "audio.ssd139"
            }
          }
        },
        {
          "@type": "ml:Field",
          "name": "audio_ssd140",
          "dataType": "sc:Integer",
          "source": {
            "distribution": "birds.arff",
            "extract": {
              "column": "audio.ssd140"
            }
          }
        },
        {
          "@type": "ml:Field",
          "name": "audio_ssd141",
          "dataType": "sc:Integer",
          "source": {
            "distribution": "birds.arff",
            "extract": {
              "column": "audio.ssd141"
            }
          }
        },
        {
          "@type": "ml:Field",
          "name": "audio_ssd145",
          "dataType": "sc:Integer",
          "source": {
            "distribution": "birds.arff",
            "extract": {
              "column": "audio.ssd145"
            }
          }
        },
        {
          "@type": "ml:Field",
          "name": "audio_ssd146",
          "dataType": "sc:Integer",
          "source": {
            "distribution": "birds.arff",
            "extract": {
              "column": "audio.ssd146"
            }
          }
        },
        {
          "@type": "ml:Field",
          "name": "audio_ssd147",
          "dataType": "sc:Integer",
          "source": {
            "distribution": "birds.arff",
            "extract": {
              "column": "audio.ssd147"
            }
          }
        },
        {
          "@type": "ml:Field",
          "name": "audio_ssd148",
          "dataType": "sc:Integer",
          "source": {
            "distribution": "birds.arff",
            "extract": {
              "column": "audio.ssd148"
            }
          }
        },
        {
          "@type": "ml:Field",
          "name": "audio_ssd149",
          "dataType": "sc:Integer",
          "source": {
            "distribution": "birds.arff",
            "extract": {
              "column": "audio.ssd149"
            }
          }
        },
        {
          "@type": "ml:Field",
          "name": "audio_ssd150",
          "dataType": "sc:Integer",
          "source": {
            "distribution": "birds.arff",
            "extract": {
              "column": "audio.ssd150"
            }
          }
        },
        {
          "@type": "ml:Field",
          "name": "audio_ssd151",
          "dataType": "sc:Integer",
          "source": {
            "distribution": "birds.arff",
            "extract": {
              "column": "audio.ssd151"
            }
          }
        },
        {
          "@type": "ml:Field",
          "name": "audio_ssd152",
          "dataType": "sc:Integer",
          "source": {
            "distribution": "birds.arff",
            "extract": {
              "column": "audio.ssd152"
            }
          }
        },
        {
          "@type": "ml:Field",
          "name": "audio_ssd153",
          "dataType": "sc:Integer",
          "source": {
            "distribution": "birds.arff",
            "extract": {
              "column": "audio.ssd153"
            }
          }
        },
        {
          "@type": "ml:Field",
          "name": "audio_ssd154",
          "dataType": "sc:Integer",
          "source": {
            "distribution": "birds.arff",
            "extract": {
              "column": "audio.ssd154"
            }
          }
        },
        {
          "@type": "ml:Field",
          "name": "audio_ssd155",
          "dataType": "sc:Integer",
          "source": {
            "distribution": "birds.arff",
            "extract": {
              "column": "audio.ssd155"
            }
          }
        },
        {
          "@type": "ml:Field",
          "name": "audio_ssd156",
          "dataType": "sc:Integer",
          "source": {
            "distribution": "birds.arff",
            "extract": {
              "column": "audio.ssd156"
            }
          }
        },
        {
          "@type": "ml:Field",
          "name": "audio_ssd157",
          "dataType": "sc:Integer",
          "source": {
            "distribution": "birds.arff",
            "extract": {
              "column": "audio.ssd157"
            }
          }
        },
        {
          "@type": "ml:Field",
          "name": "audio_ssd158",
          "dataType": "sc:Integer",
          "source": {
            "distribution": "birds.arff",
            "extract": {
              "column": "audio.ssd158"
            }
          }
        },
        {
          "@type": "ml:Field",
          "name": "audio_ssd159",
          "dataType": "sc:Integer",
          "source": {
            "distribution": "birds.arff",
            "extract": {
              "column": "audio.ssd159"
            }
          }
        },
        {
          "@type": "ml:Field",
          "name": "audio_ssd160",
          "dataType": "sc:Integer",
          "source": {
            "distribution": "birds.arff",
            "extract": {
              "column": "audio.ssd160"
            }
          }
        },
        {
          "@type": "ml:Field",
          "name": "audio_ssd161",
          "dataType": "sc:Integer",
          "source": {
            "distribution": "birds.arff",
            "extract": {
              "column": "audio.ssd161"
            }
          }
        },
        {
          "@type": "ml:Field",
          "name": "audio_ssd162",
          "dataType": "sc:Integer",
          "source": {
            "distribution": "birds.arff",
            "extract": {
              "column": "audio.ssd162"
            }
          }
        },
        {
          "@type": "ml:Field",
          "name": "audio_ssd163",
          "dataType": "sc:Integer",
          "source": {
            "distribution": "birds.arff",
            "extract": {
              "column": "audio.ssd163"
            }
          }
        },
        {
          "@type": "ml:Field",
          "name": "audio_ssd164",
          "dataType": "sc:Integer",
          "source": {
            "distribution": "birds.arff",
            "extract": {
              "column": "audio.ssd164"
            }
          }
        },
        {
          "@type": "ml:Field",
          "name": "audio_ssd165",
          "dataType": "sc:Integer",
          "source": {
            "distribution": "birds.arff",
            "extract": {
              "column": "audio.ssd165"
            }
          }
        },
        {
          "@type": "ml:Field",
          "name": "audio_ssd166",
          "dataType": "sc:Integer",
          "source": {
            "distribution": "birds.arff",
            "extract": {
              "column": "audio.ssd166"
            }
          }
        },
        {
          "@type": "ml:Field",
          "name": "cluster1",
          "dataType": "sc:Integer",
          "source": {
            "distribution": "birds.arff",
            "extract": {
              "column": "cluster1"
            }
          }
        },
        {
          "@type": "ml:Field",
          "name": "cluster2",
          "dataType": "sc:Integer",
          "source": {
            "distribution": "birds.arff",
            "extract": {
              "column": "cluster2"
            }
          }
        },
        {
          "@type": "ml:Field",
          "name": "cluster3",
          "dataType": "sc:Integer",
          "source": {
            "distribution": "birds.arff",
            "extract": {
              "column": "cluster3"
            }
          }
        },
        {
          "@type": "ml:Field",
          "name": "cluster4",
          "dataType": "sc:Integer",
          "source": {
            "distribution": "birds.arff",
            "extract": {
              "column": "cluster4"
            }
          }
        },
        {
          "@type": "ml:Field",
          "name": "cluster5",
          "dataType": "sc:Integer",
          "source": {
            "distribution": "birds.arff",
            "extract": {
              "column": "cluster5"
            }
          }
        },
        {
          "@type": "ml:Field",
          "name": "cluster6",
          "dataType": "sc:Integer",
          "source": {
            "distribution": "birds.arff",
            "extract": {
              "column": "cluster6"
            }
          }
        },
        {
          "@type": "ml:Field",
          "name": "cluster7",
          "dataType": "sc:Integer",
          "source": {
            "distribution": "birds.arff",
            "extract": {
              "column": "cluster7"
            }
          }
        },
        {
          "@type": "ml:Field",
          "name": "cluster8",
          "dataType": "sc:Integer",
          "source": {
            "distribution": "birds.arff",
            "extract": {
              "column": "cluster8"
            }
          }
        },
        {
          "@type": "ml:Field",
          "name": "cluster9",
          "dataType": "sc:Integer",
          "source": {
            "distribution": "birds.arff",
            "extract": {
              "column": "cluster9"
            }
          }
        },
        {
          "@type": "ml:Field",
          "name": "cluster10",
          "dataType": "sc:Integer",
          "source": {
            "distribution": "birds.arff",
            "extract": {
              "column": "cluster10"
            }
          }
        },
        {
          "@type": "ml:Field",
          "name": "cluster11",
          "dataType": "sc:Integer",
          "source": {
            "distribution": "birds.arff",
            "extract": {
              "column": "cluster11"
            }
          }
        },
        {
          "@type": "ml:Field",
          "name": "cluster12",
          "dataType": "sc:Integer",
          "source": {
            "distribution": "birds.arff",
            "extract": {
              "column": "cluster12"
            }
          }
        },
        {
          "@type": "ml:Field",
          "name": "cluster13",
          "dataType": "sc:Integer",
          "source": {
            "distribution": "birds.arff",
            "extract": {
              "column": "cluster13"
            }
          }
        },
        {
          "@type": "ml:Field",
          "name": "cluster14",
          "dataType": "sc:Integer",
          "source": {
            "distribution": "birds.arff",
            "extract": {
              "column": "cluster14"
            }
          }
        },
        {
          "@type": "ml:Field",
          "name": "cluster15",
          "dataType": "sc:Integer",
          "source": {
            "distribution": "birds.arff",
            "extract": {
              "column": "cluster15"
            }
          }
        },
        {
          "@type": "ml:Field",
          "name": "cluster16",
          "dataType": "sc:Integer",
          "source": {
            "distribution": "birds.arff",
            "extract": {
              "column": "cluster16"
            }
          }
        },
        {
          "@type": "ml:Field",
          "name": "cluster17",
          "dataType": "sc:Integer",
          "source": {
            "distribution": "birds.arff",
            "extract": {
              "column": "cluster17"
            }
          }
        },
        {
          "@type": "ml:Field",
          "name": "cluster18",
          "dataType": "sc:Integer",
          "source": {
            "distribution": "birds.arff",
            "extract": {
              "column": "cluster18"
            }
          }
        },
        {
          "@type": "ml:Field",
          "name": "cluster19",
          "dataType": "sc:Integer",
          "source": {
            "distribution": "birds.arff",
            "extract": {
              "column": "cluster19"
            }
          }
        },
        {
          "@type": "ml:Field",
          "name": "cluster20",
          "dataType": "sc:Integer",
          "source": {
            "distribution": "birds.arff",
            "extract": {
              "column": "cluster20"
            }
          }
        },
        {
          "@type": "ml:Field",
          "name": "cluster21",
          "dataType": "sc:Integer",
          "source": {
            "distribution": "birds.arff",
            "extract": {
              "column": "cluster21"
            }
          }
        },
        {
          "@type": "ml:Field",
          "name": "cluster22",
          "dataType": "sc:Integer",
          "source": {
            "distribution": "birds.arff",
            "extract": {
              "column": "cluster22"
            }
          }
        },
        {
          "@type": "ml:Field",
          "name": "cluster23",
          "dataType": "sc:Integer",
          "source": {
            "distribution": "birds.arff",
            "extract": {
              "column": "cluster23"
            }
          }
        },
        {
          "@type": "ml:Field",
          "name": "cluster24",
          "dataType": "sc:Integer",
          "source": {
            "distribution": "birds.arff",
            "extract": {
              "column": "cluster24"
            }
          }
        },
        {
          "@type": "ml:Field",
          "name": "cluster25",
          "dataType": "sc:Integer",
          "source": {
            "distribution": "birds.arff",
            "extract": {
              "column": "cluster25"
            }
          }
        },
        {
          "@type": "ml:Field",
          "name": "cluster26",
          "dataType": "sc:Integer",
          "source": {
            "distribution": "birds.arff",
            "extract": {
              "column": "cluster26"
            }
          }
        },
        {
          "@type": "ml:Field",
          "name": "cluster27",
          "dataType": "sc:Integer",
          "source": {
            "distribution": "birds.arff",
            "extract": {
              "column": "cluster27"
            }
          }
        },
        {
          "@type": "ml:Field",
          "name": "cluster28",
          "dataType": "sc:Integer",
          "source": {
            "distribution": "birds.arff",
            "extract": {
              "column": "cluster28"
            }
          }
        },
        {
          "@type": "ml:Field",
          "name": "cluster29",
          "dataType": "sc:Integer",
          "source": {
            "distribution": "birds.arff",
            "extract": {
              "column": "cluster29"
            }
          }
        },
        {
          "@type": "ml:Field",
          "name": "cluster30",
          "dataType": "sc:Integer",
          "source": {
            "distribution": "birds.arff",
            "extract": {
              "column": "cluster30"
            }
          }
        },
        {
          "@type": "ml:Field",
          "name": "cluster31",
          "dataType": "sc:Integer",
          "source": {
            "distribution": "birds.arff",
            "extract": {
              "column": "cluster31"
            }
          }
        },
        {
          "@type": "ml:Field",
          "name": "cluster32",
          "dataType": "sc:Integer",
          "source": {
            "distribution": "birds.arff",
            "extract": {
              "column": "cluster32"
            }
          }
        },
        {
          "@type": "ml:Field",
          "name": "cluster33",
          "dataType": "sc:Integer",
          "source": {
            "distribution": "birds.arff",
            "extract": {
              "column": "cluster33"
            }
          }
        },
        {
          "@type": "ml:Field",
          "name": "cluster34",
          "dataType": "sc:Integer",
          "source": {
            "distribution": "birds.arff",
            "extract": {
              "column": "cluster34"
            }
          }
        },
        {
          "@type": "ml:Field",
          "name": "cluster35",
          "dataType": "sc:Integer",
          "source": {
            "distribution": "birds.arff",
            "extract": {
              "column": "cluster35"
            }
          }
        },
        {
          "@type": "ml:Field",
          "name": "cluster36",
          "dataType": "sc:Integer",
          "source": {
            "distribution": "birds.arff",
            "extract": {
              "column": "cluster36"
            }
          }
        },
        {
          "@type": "ml:Field",
          "name": "cluster37",
          "dataType": "sc:Integer",
          "source": {
            "distribution": "birds.arff",
            "extract": {
              "column": "cluster37"
            }
          }
        },
        {
          "@type": "ml:Field",
          "name": "cluster38",
          "dataType": "sc:Integer",
          "source": {
            "distribution": "birds.arff",
            "extract": {
              "column": "cluster38"
            }
          }
        },
        {
          "@type": "ml:Field",
          "name": "cluster39",
          "dataType": "sc:Integer",
          "source": {
            "distribution": "birds.arff",
            "extract": {
              "column": "cluster39"
            }
          }
        },
        {
          "@type": "ml:Field",
          "name": "cluster40",
          "dataType": "sc:Integer",
          "source": {
            "distribution": "birds.arff",
            "extract": {
              "column": "cluster40"
            }
          }
        },
        {
          "@type": "ml:Field",
          "name": "cluster41",
          "dataType": "sc:Integer",
          "source": {
            "distribution": "birds.arff",
            "extract": {
              "column": "cluster41"
            }
          }
        },
        {
          "@type": "ml:Field",
          "name": "cluster42",
          "dataType": "sc:Integer",
          "source": {
            "distribution": "birds.arff",
            "extract": {
              "column": "cluster42"
            }
          }
        },
        {
          "@type": "ml:Field",
          "name": "cluster43",
          "dataType": "sc:Integer",
          "source": {
            "distribution": "birds.arff",
            "extract": {
              "column": "cluster43"
            }
          }
        },
        {
          "@type": "ml:Field",
          "name": "cluster44",
          "dataType": "sc:Integer",
          "source": {
            "distribution": "birds.arff",
            "extract": {
              "column": "cluster44"
            }
          }
        },
        {
          "@type": "ml:Field",
          "name": "cluster45",
          "dataType": "sc:Integer",
          "source": {
            "distribution": "birds.arff",
            "extract": {
              "column": "cluster45"
            }
          }
        },
        {
          "@type": "ml:Field",
          "name": "cluster46",
          "dataType": "sc:Integer",
          "source": {
            "distribution": "birds.arff",
            "extract": {
              "column": "cluster46"
            }
          }
        },
        {
          "@type": "ml:Field",
          "name": "cluster47",
          "dataType": "sc:Integer",
          "source": {
            "distribution": "birds.arff",
            "extract": {
              "column": "cluster47"
            }
          }
        },
        {
          "@type": "ml:Field",
          "name": "cluster48",
          "dataType": "sc:Integer",
          "source": {
            "distribution": "birds.arff",
            "extract": {
              "column": "cluster48"
            }
          }
        },
        {
          "@type": "ml:Field",
          "name": "cluster49",
          "dataType": "sc:Integer",
          "source": {
            "distribution": "birds.arff",
            "extract": {
              "column": "cluster49"
            }
          }
        },
        {
          "@type": "ml:Field",
          "name": "cluster50",
          "dataType": "sc:Integer",
          "source": {
            "distribution": "birds.arff",
            "extract": {
              "column": "cluster50"
            }
          }
        },
        {
          "@type": "ml:Field",
          "name": "cluster51",
          "dataType": "sc:Integer",
          "source": {
            "distribution": "birds.arff",
            "extract": {
              "column": "cluster51"
            }
          }
        },
        {
          "@type": "ml:Field",
          "name": "cluster52",
          "dataType": "sc:Integer",
          "source": {
            "distribution": "birds.arff",
            "extract": {
              "column": "cluster52"
            }
          }
        },
        {
          "@type": "ml:Field",
          "name": "cluster53",
          "dataType": "sc:Integer",
          "source": {
            "distribution": "birds.arff",
            "extract": {
              "column": "cluster53"
            }
          }
        },
        {
          "@type": "ml:Field",
          "name": "cluster54",
          "dataType": "sc:Integer",
          "source": {
            "distribution": "birds.arff",
            "extract": {
              "column": "cluster54"
            }
          }
        },
        {
          "@type": "ml:Field",
          "name": "cluster55",
          "dataType": "sc:Integer",
          "source": {
            "distribution": "birds.arff",
            "extract": {
              "column": "cluster55"
            }
          }
        },
        {
          "@type": "ml:Field",
          "name": "cluster56",
          "dataType": "sc:Integer",
          "source": {
            "distribution": "birds.arff",
            "extract": {
              "column": "cluster56"
            }
          }
        },
        {
          "@type": "ml:Field",
          "name": "cluster57",
          "dataType": "sc:Integer",
          "source": {
            "distribution": "birds.arff",
            "extract": {
              "column": "cluster57"
            }
          }
        },
        {
          "@type": "ml:Field",
          "name": "cluster59",
          "dataType": "sc:Integer",
          "source": {
            "distribution": "birds.arff",
            "extract": {
              "column": "cluster59"
            }
          }
        },
        {
          "@type": "ml:Field",
          "name": "cluster60",
          "dataType": "sc:Integer",
          "source": {
            "distribution": "birds.arff",
            "extract": {
              "column": "cluster60"
            }
          }
        },
        {
          "@type": "ml:Field",
          "name": "cluster61",
          "dataType": "sc:Integer",
          "source": {
            "distribution": "birds.arff",
            "extract": {
              "column": "cluster61"
            }
          }
        },
        {
          "@type": "ml:Field",
          "name": "cluster62",
          "dataType": "sc:Integer",
          "source": {
            "distribution": "birds.arff",
            "extract": {
              "column": "cluster62"
            }
          }
        },
        {
          "@type": "ml:Field",
          "name": "cluster63",
          "dataType": "sc:Integer",
          "source": {
            "distribution": "birds.arff",
            "extract": {
              "column": "cluster63"
            }
          }
        },
        {
          "@type": "ml:Field",
          "name": "cluster64",
          "dataType": "sc:Integer",
          "source": {
            "distribution": "birds.arff",
            "extract": {
              "column": "cluster64"
            }
          }
        },
        {
          "@type": "ml:Field",
          "name": "cluster65",
          "dataType": "sc:Integer",
          "source": {
            "distribution": "birds.arff",
            "extract": {
              "column": "cluster65"
            }
          }
        },
        {
          "@type": "ml:Field",
          "name": "cluster66",
          "dataType": "sc:Integer",
          "source": {
            "distribution": "birds.arff",
            "extract": {
              "column": "cluster66"
            }
          }
        },
        {
          "@type": "ml:Field",
          "name": "cluster67",
          "dataType": "sc:Integer",
          "source": {
            "distribution": "birds.arff",
            "extract": {
              "column": "cluster67"
            }
          }
        },
        {
          "@type": "ml:Field",
          "name": "cluster68",
          "dataType": "sc:Integer",
          "source": {
            "distribution": "birds.arff",
            "extract": {
              "column": "cluster68"
            }
          }
        },
        {
          "@type": "ml:Field",
          "name": "cluster69",
          "dataType": "sc:Integer",
          "source": {
            "distribution": "birds.arff",
            "extract": {
              "column": "cluster69"
            }
          }
        },
        {
          "@type": "ml:Field",
          "name": "cluster70",
          "dataType": "sc:Integer",
          "source": {
            "distribution": "birds.arff",
            "extract": {
              "column": "cluster70"
            }
          }
        },
        {
          "@type": "ml:Field",
          "name": "cluster71",
          "dataType": "sc:Integer",
          "source": {
            "distribution": "birds.arff",
            "extract": {
              "column": "cluster71"
            }
          }
        },
        {
          "@type": "ml:Field",
          "name": "cluster72",
          "dataType": "sc:Integer",
          "source": {
            "distribution": "birds.arff",
            "extract": {
              "column": "cluster72"
            }
          }
        },
        {
          "@type": "ml:Field",
          "name": "cluster73",
          "dataType": "sc:Integer",
          "source": {
            "distribution": "birds.arff",
            "extract": {
              "column": "cluster73"
            }
          }
        },
        {
          "@type": "ml:Field",
          "name": "cluster74",
          "dataType": "sc:Integer",
          "source": {
            "distribution": "birds.arff",
            "extract": {
              "column": "cluster74"
            }
          }
        },
        {
          "@type": "ml:Field",
          "name": "cluster75",
          "dataType": "sc:Integer",
          "source": {
            "distribution": "birds.arff",
            "extract": {
              "column": "cluster75"
            }
          }
        },
        {
          "@type": "ml:Field",
          "name": "cluster76",
          "dataType": "sc:Integer",
          "source": {
            "distribution": "birds.arff",
            "extract": {
              "column": "cluster76"
            }
          }
        },
        {
          "@type": "ml:Field",
          "name": "cluster78",
          "dataType": "sc:Integer",
          "source": {
            "distribution": "birds.arff",
            "extract": {
              "column": "cluster78"
            }
          }
        },
        {
          "@type": "ml:Field",
          "name": "cluster79",
          "dataType": "sc:Integer",
          "source": {
            "distribution": "birds.arff",
            "extract": {
              "column": "cluster79"
            }
          }
        },
        {
          "@type": "ml:Field",
          "name": "cluster80",
          "dataType": "sc:Integer",
          "source": {
            "distribution": "birds.arff",
            "extract": {
              "column": "cluster80"
            }
          }
        },
        {
          "@type": "ml:Field",
          "name": "cluster81",
          "dataType": "sc:Integer",
          "source": {
            "distribution": "birds.arff",
            "extract": {
              "column": "cluster81"
            }
          }
        },
        {
          "@type": "ml:Field",
          "name": "cluster82",
          "dataType": "sc:Integer",
          "source": {
            "distribution": "birds.arff",
            "extract": {
              "column": "cluster82"
            }
          }
        },
        {
          "@type": "ml:Field",
          "name": "cluster83",
          "dataType": "sc:Integer",
          "source": {
            "distribution": "birds.arff",
            "extract": {
              "column": "cluster83"
            }
          }
        },
        {
          "@type": "ml:Field",
          "name": "cluster84",
          "dataType": "sc:Integer",
          "source": {
            "distribution": "birds.arff",
            "extract": {
              "column": "cluster84"
            }
          }
        },
        {
          "@type": "ml:Field",
          "name": "cluster85",
          "dataType": "sc:Integer",
          "source": {
            "distribution": "birds.arff",
            "extract": {
              "column": "cluster85"
            }
          }
        },
        {
          "@type": "ml:Field",
          "name": "cluster86",
          "dataType": "sc:Integer",
          "source": {
            "distribution": "birds.arff",
            "extract": {
              "column": "cluster86"
            }
          }
        },
        {
          "@type": "ml:Field",
          "name": "cluster87",
          "dataType": "sc:Integer",
          "source": {
            "distribution": "birds.arff",
            "extract": {
              "column": "cluster87"
            }
          }
        },
        {
          "@type": "ml:Field",
          "name": "cluster88",
          "dataType": "sc:Integer",
          "source": {
            "distribution": "birds.arff",
            "extract": {
              "column": "cluster88"
            }
          }
        },
        {
          "@type": "ml:Field",
          "name": "cluster89",
          "dataType": "sc:Integer",
          "source": {
            "distribution": "birds.arff",
            "extract": {
              "column": "cluster89"
            }
          }
        },
        {
          "@type": "ml:Field",
          "name": "cluster90",
          "dataType": "sc:Integer",
          "source": {
            "distribution": "birds.arff",
            "extract": {
              "column": "cluster90"
            }
          }
        },
        {
          "@type": "ml:Field",
          "name": "cluster91",
          "dataType": "sc:Integer",
          "source": {
            "distribution": "birds.arff",
            "extract": {
              "column": "cluster91"
            }
          }
        },
        {
          "@type": "ml:Field",
          "name": "cluster92",
          "dataType": "sc:Integer",
          "source": {
            "distribution": "birds.arff",
            "extract": {
              "column": "cluster92"
            }
          }
        },
        {
          "@type": "ml:Field",
          "name": "cluster93",
          "dataType": "sc:Integer",
          "source": {
            "distribution": "birds.arff",
            "extract": {
              "column": "cluster93"
            }
          }
        },
        {
          "@type": "ml:Field",
          "name": "cluster94",
          "dataType": "sc:Integer",
          "source": {
            "distribution": "birds.arff",
            "extract": {
              "column": "cluster94"
            }
          }
        },
        {
          "@type": "ml:Field",
          "name": "cluster95",
          "dataType": "sc:Integer",
          "source": {
            "distribution": "birds.arff",
            "extract": {
              "column": "cluster95"
            }
          }
        },
        {
          "@type": "ml:Field",
          "name": "cluster96",
          "dataType": "sc:Integer",
          "source": {
            "distribution": "birds.arff",
            "extract": {
              "column": "cluster96"
            }
          }
        },
        {
          "@type": "ml:Field",
          "name": "cluster97",
          "dataType": "sc:Integer",
          "source": {
            "distribution": "birds.arff",
            "extract": {
              "column": "cluster97"
            }
          }
        },
        {
          "@type": "ml:Field",
          "name": "cluster98",
          "dataType": "sc:Integer",
          "source": {
            "distribution": "birds.arff",
            "extract": {
              "column": "cluster98"
            }
          }
        },
        {
          "@type": "ml:Field",
          "name": "cluster99",
          "dataType": "sc:Integer",
          "source": {
            "distribution": "birds.arff",
            "extract": {
              "column": "cluster99"
            }
          }
        },
        {
          "@type": "ml:Field",
          "name": "cluster100",
          "dataType": "sc:Integer",
          "source": {
            "distribution": "birds.arff",
            "extract": {
              "column": "cluster100"
            }
          }
        },
        {
          "@type": "ml:Field",
          "name": "segments",
          "dataType": "sc:Integer",
          "source": {
            "distribution": "birds.arff",
            "extract": {
              "column": "segments"
            }
          }
        },
        {
          "@type": "ml:Field",
          "name": "mean_rect_width",
          "dataType": "sc:Integer",
          "source": {
            "distribution": "birds.arff",
            "extract": {
              "column": "mean_rect_width"
            }
          }
        },
        {
          "@type": "ml:Field",
          "name": "std_rect_width",
          "dataType": "sc:Integer",
          "source": {
            "distribution": "birds.arff",
            "extract": {
              "column": "std_rect_width"
            }
          }
        },
        {
          "@type": "ml:Field",
          "name": "mean_rect_height",
          "dataType": "sc:Integer",
          "source": {
            "distribution": "birds.arff",
            "extract": {
              "column": "mean_rect_height"
            }
          }
        },
        {
          "@type": "ml:Field",
          "name": "std_rect_height",
          "dataType": "sc:Integer",
          "source": {
            "distribution": "birds.arff",
            "extract": {
              "column": "std_rect_height"
            }
          }
        },
        {
          "@type": "ml:Field",
          "name": "mean_rect_volume",
          "dataType": "sc:Integer",
          "source": {
            "distribution": "birds.arff",
            "extract": {
              "column": "mean_rect_volume"
            }
          }
        },
        {
          "@type": "ml:Field",
          "name": "std_rect_volume",
          "dataType": "sc:Integer",
          "source": {
            "distribution": "birds.arff",
            "extract": {
              "column": "std_rect_volume"
            }
          }
        },
        {
          "@type": "ml:Field",
          "name": "hassegments",
          "dataType": "sc:Boolean",
          "source": {
            "distribution": "birds.arff",
            "extract": {
              "column": "hasSegments"
            }
          }
        },
        {
          "@type": "ml:Field",
          "name": "location",
          "dataType": "sc:Text",
          "source": {
            "distribution": "birds.arff",
            "extract": {
              "column": "location"
            }
          }
        },
        {
          "@type": "ml:Field",
          "name": "brown_creeper",
          "dataType": "sc:Boolean",
          "source": {
            "distribution": "birds.arff",
            "extract": {
              "column": "Brown.Creeper"
            }
          }
        },
        {
          "@type": "ml:Field",
          "name": "pacific_wren",
          "dataType": "sc:Boolean",
          "source": {
            "distribution": "birds.arff",
            "extract": {
              "column": "Pacific.Wren"
            }
          }
        },
        {
          "@type": "ml:Field",
          "name": "pacific_slope_flycatcher",
          "dataType": "sc:Boolean",
          "source": {
            "distribution": "birds.arff",
            "extract": {
              "column": "Pacific.slope.Flycatcher"
            }
          }
        },
        {
          "@type": "ml:Field",
          "name": "red_breasted_nuthatch",
          "dataType": "sc:Boolean",
          "source": {
            "distribution": "birds.arff",
            "extract": {
              "column": "Red.breasted.Nuthatch"
            }
          }
        },
        {
          "@type": "ml:Field",
          "name": "dark_eyed_junco",
          "dataType": "sc:Boolean",
          "source": {
            "distribution": "birds.arff",
            "extract": {
              "column": "Dark.eyed.Junco"
            }
          }
        },
        {
          "@type": "ml:Field",
          "name": "olive_sided_flycatcher",
          "dataType": "sc:Boolean",
          "source": {
            "distribution": "birds.arff",
            "extract": {
              "column": "Olive.sided.Flycatcher"
            }
          }
        },
        {
          "@type": "ml:Field",
          "name": "hermit_thrush",
          "dataType": "sc:Boolean",
          "source": {
            "distribution": "birds.arff",
            "extract": {
              "column": "Hermit.Thrush"
            }
          }
        },
        {
          "@type": "ml:Field",
          "name": "chestnut_backed_chickadee",
          "dataType": "sc:Boolean",
          "source": {
            "distribution": "birds.arff",
            "extract": {
              "column": "Chestnut.backed.Chickadee"
            }
          }
        },
        {
          "@type": "ml:Field",
          "name": "varied_thrush",
          "dataType": "sc:Boolean",
          "source": {
            "distribution": "birds.arff",
            "extract": {
              "column": "Varied.Thrush"
            }
          }
        },
        {
          "@type": "ml:Field",
          "name": "hermit_warbler",
          "dataType": "sc:Boolean",
          "source": {
            "distribution": "birds.arff",
            "extract": {
              "column": "Hermit.Warbler"
            }
          }
        },
        {
          "@type": "ml:Field",
          "name": "swainson_s_thrush",
          "dataType": "sc:Boolean",
          "source": {
            "distribution": "birds.arff",
            "extract": {
              "column": "Swainson.s.Thrush"
            }
          }
        },
        {
          "@type": "ml:Field",
          "name": "hammond_s_flycatcher",
          "dataType": "sc:Boolean",
          "source": {
            "distribution": "birds.arff",
            "extract": {
              "column": "Hammond.s.Flycatcher"
            }
          }
        },
        {
          "@type": "ml:Field",
          "name": "western_tanager",
          "dataType": "sc:Boolean",
          "source": {
            "distribution": "birds.arff",
            "extract": {
              "column": "Western.Tanager"
            }
          }
        },
        {
          "@type": "ml:Field",
          "name": "black_headed_grosbeak",
          "dataType": "sc:Boolean",
          "source": {
            "distribution": "birds.arff",
            "extract": {
              "column": "Black.headed.Grosbeak"
            }
          }
        },
        {
          "@type": "ml:Field",
          "name": "golden_crowned_kinglet",
          "dataType": "sc:Boolean",
          "source": {
            "distribution": "birds.arff",
            "extract": {
              "column": "Golden.Crowned.Kinglet"
            }
          }
        },
        {
          "@type": "ml:Field",
          "name": "warbling_vireo",
          "dataType": "sc:Boolean",
          "source": {
            "distribution": "birds.arff",
            "extract": {
              "column": "Warbling.Vireo"
            }
          }
        },
        {
          "@type": "ml:Field",
          "name": "macgillivray_s_warbler",
          "dataType": "sc:Boolean",
          "source": {
            "distribution": "birds.arff",
            "extract": {
              "column": "MacGillivray.s.Warbler"
            }
          }
        },
        {
          "@type": "ml:Field",
          "name": "stellar_s_jay",
          "dataType": "sc:Boolean",
          "source": {
            "distribution": "birds.arff",
            "extract": {
              "column": "Stellar.s.Jay"
            }
          }
        },
        {
          "@type": "ml:Field",
          "name": "common_nighthawk",
          "dataType": "sc:Boolean",
          "source": {
            "distribution": "birds.arff",
            "extract": {
              "column": "Common.Nighthawk"
            }
          }
        }
      ]
    }
  ]
}
